OllamaTamil/__init__.py
OllamaTamil/main.py
ollamatamil-0.1.dist-info/METADATA
ollamatamil-0.1.dist-info/WHEEL
ollamatamil-0.1.dist-info/top_level.txt
ollamatamil-0.1.dist-info/RECORD
