Metadata-Version: 2.4
Name: OllamaTamil
Version: 0.1
Summary: Ollama tamil helps you to build ollama api but with tamil interface
Dynamic: summary
